cuti/__init__.py
cuti/__main__.py
cuti/claude_usage_monitor.py
cuti/agents/__init__.py
cuti/agents/base.py
cuti/agents/claude_agent.py
cuti/agents/context.py
cuti/agents/gemini_agent.py
cuti/agents/pool.py
cuti/agents/router.py
cuti/cli/__init__.py
cuti/cli/app.py
cuti/cli/utils.py
cuti/cli/commands/__init__.py
cuti/cli/commands/agent.py
cuti/cli/commands/alias.py
cuti/cli/commands/container.py
cuti/cli/commands/container_status.py
cuti/cli/commands/devcontainer.py
cuti/cli/commands/favorites.py
cuti/cli/commands/queue.py
cuti/cli/commands/settings.py
cuti/cli/commands/sync.py
cuti/cli/commands/todo.py
cuti/cli/commands/tools.py
cuti/core/__init__.py
cuti/core/claude_interface.py
cuti/core/claude_sdk_interface.py
cuti/core/claude_stream_interface.py
cuti/core/config.py
cuti/core/mock_stream_interface.py
cuti/core/models.py
cuti/core/prompt_prefix.py
cuti/core/queue.py
cuti/core/storage.py
cuti/core/todo_models.py
cuti/core/token_counter.py
cuti/prompts/builtin_agents/__init__.py
cuti/prompts/builtin_agents/code-reviewer.md
cuti/prompts/builtin_agents/docs-generator.md
cuti/prompts/builtin_agents/gemini-codebase-analysis.md
cuti/prompts/builtin_agents/refactor-assistant.md
cuti/prompts/builtin_agents/test-writer.md
cuti/prompts/builtin_agents/ui-design-expert.md
cuti/prompts/prompt_prefixes/code_reviewer.json
cuti/prompts/prompt_prefixes/data_scientist.json
cuti/prompts/prompt_prefixes/debugger.json
cuti/prompts/prompt_prefixes/devops_engineer.json
cuti/prompts/prompt_prefixes/minimal.json
cuti/prompts/prompt_prefixes/software_engineer.json
cuti/services/__init__.py
cuti/services/agent_manager.py
cuti/services/aliases.py
cuti/services/claude_agent_manager.py
cuti/services/claude_logs_reader.py
cuti/services/claude_monitor_integration.py
cuti/services/claude_orchestration.py
cuti/services/claude_settings_manager.py
cuti/services/claude_todo_sync.py
cuti/services/claude_usage_monitor.py
cuti/services/container_usage_sync.py
cuti/services/devcontainer.py
cuti-0.1.65.dist-info/METADATA
cuti-0.1.65.dist-info/WHEEL
cuti-0.1.65.dist-info/entry_points.txt
cuti-0.1.65.dist-info/licenses/LICENSE
cuti-0.1.65.dist-info/RECORD
