Metadata-Version: 2.4
Name: cuti
Version: 0.1.65
Summary: Production-ready Claude Code utilities with command queuing, prompt aliases, web interface, and monitoring.
Project-URL: Documentation, https://github.com/nociza/cuti/blob/main/README.md
Project-URL: Homepage, https://github.com/nociza/cuti
Project-URL: Issues, https://github.com/nociza/cuti/issues
Project-URL: Repository, https://github.com/nociza/cuti
Author: claude-code, nociza
License-Expression: Apache-2.0
License-File: LICENSE
Keywords: ai,automation,claude,cli,orchestration,queue
Classifier: Development Status :: 4 - Beta
Classifier: Intended Audience :: Developers
Classifier: License :: OSI Approved :: Apache Software License
Classifier: Programming Language :: Python :: 3
Classifier: Programming Language :: Python :: 3.10
Classifier: Programming Language :: Python :: 3.11
Classifier: Programming Language :: Python :: 3.12
Classifier: Topic :: Software Development :: Libraries :: Python Modules
Classifier: Topic :: System :: Systems Administration
Classifier: Topic :: Utilities
Requires-Python: >=3.10
Requires-Dist: aiofiles>=23.0.0
Requires-Dist: anyio>=4.10.0
Requires-Dist: claude-code-sdk>=0.0.20
Requires-Dist: claude-monitor>=3.1.0
Requires-Dist: fastapi>=0.104.0
Requires-Dist: httpx>=0.25.0
Requires-Dist: jinja2>=3.1.0
Requires-Dist: psutil>=5.9.0
Requires-Dist: python-multipart>=0.0.6
Requires-Dist: pyyaml>=6.0
Requires-Dist: requests>=2.32.4
Requires-Dist: rich>=13.0.0
Requires-Dist: typer>=0.9.0
Requires-Dist: uvicorn[standard]>=0.24.0
Requires-Dist: websockets>=12.0
Provides-Extra: container
Requires-Dist: docker>=6.0.0; extra == 'container'
Provides-Extra: dev
Requires-Dist: black>=23.0.0; extra == 'dev'
Requires-Dist: mypy>=1.6.0; extra == 'dev'
Requires-Dist: pre-commit>=3.5.0; extra == 'dev'
Requires-Dist: pytest-asyncio>=0.21.0; extra == 'dev'
Requires-Dist: pytest>=7.4.0; extra == 'dev'
Requires-Dist: ruff>=0.1.0; extra == 'dev'
